research/__init__.py
research/router_logic.py
research/step_parser_logic.py
g3lu_res-0.0.1.dist-info/METADATA
g3lu_res-0.0.1.dist-info/WHEEL
g3lu_res-0.0.1.dist-info/top_level.txt
g3lu_res-0.0.1.dist-info/RECORD
